{
  "core": "0.22.0",
  "coreNotes": "## New Features\n- **Markdown Rendering Support**: Release notes in update notification popups now support Markdown format parsing, with a new universal Markdown parsing utility module for improved formatting and readability\n\n<details>\n<summary>中文说明</summary>\n\n# v0.22.0 更新说明 (2026-07-15)\n\n## 新增功能\n- **Markdown 渲染支持**: 更新通知弹窗中的版本说明支持 Markdown 格式解析，新增通用 Markdown 解析工具模块，提升更新信息的排版和可读性\n\n</details>",
  "pubDate": "2026-07-15T01:17:09.315Z",
  "plugins": {
    "pomodoro": "2.1.0",
    "proxy-switch": "2.6.0"
  }
}